Metadata-Version: 2.1
Name: superchat-cli
Version: 1.0.9
Summary: command-line interface for chatgpt
Home-page: https://github.com/quintenroets/chat
Author: Quinten Roets
Author-email: quinten.roets@gmail.com
License: MIT
Requires-Python: >=3.10
License-File: LICENSE
